setup.py
buoyantBoussinesqSimpleFlux/__init__.py
buoyantBoussinesqSimpleFlux.egg-info/PKG-INFO
buoyantBoussinesqSimpleFlux.egg-info/SOURCES.txt
buoyantBoussinesqSimpleFlux.egg-info/dependency_links.txt
buoyantBoussinesqSimpleFlux.egg-info/entry_points.txt
buoyantBoussinesqSimpleFlux.egg-info/requires.txt
buoyantBoussinesqSimpleFlux.egg-info/top_level.txt
buoyantBoussinesqSimpleFlux.egg-info/zip-safe
buoyantBoussinesqSimpleFlux/r1_6/__init__.py
buoyantBoussinesqSimpleFlux/r1_6_dev/__init__.py
buoyantBoussinesqSimpleFlux/r1_7_0/__init__.py
buoyantBoussinesqSimpleFlux/r1_7_1/__init__.py
buoyantBoussinesqSimpleFlux/r2_0_0/__init__.py
buoyantBoussinesqSimpleFlux/r2_1_0/__init__.py